cellulose/__init__.py
cellulose/version.py
cellulose/api/__init__.py
cellulose/api/cellulose_context.py
cellulose/artifact/__init__.py
cellulose/artifact/cellulose_artifact.py
cellulose/artifact/cellulose_artifact_manager.py
cellulose/base/__init__.py
cellulose/base/benchmark.py
cellulose/base/checker.py
cellulose/base/export.py
cellulose/base/loader.py
cellulose/configs/.cellulose_config.toml
cellulose/configs/__init__.py
cellulose/configs/config.py
cellulose/configs/loader.py
cellulose/dashboard/__init__.py
cellulose/dashboard/credentials.py
cellulose/dashboard/api_resources/__init__.py
cellulose/dashboard/api_resources/models/__init__.py
cellulose/dashboard/api_resources/models/onnx.py
cellulose/decorators/__init__.py
cellulose/decorators/cellulose.py
cellulose/infra/__init__.py
cellulose/metrics/__init__.py
cellulose/metrics/latency.py
cellulose/metrics/metrics.py
cellulose/onnx/__init__.py
cellulose/onnx/benchmark.py
cellulose/onnx/checker.py
cellulose/onnx/loader.py
cellulose/onnx/runtime.py
cellulose/output/__init__.py
cellulose/output/output.py
cellulose/pytorch/__init__.py
cellulose/pytorch/benchmark.py
cellulose/pytorch/export.py
cellulose/scripts/__init__.py
cellulose/tensorflow/__init__.py
cellulose/utils/__init__.py
cellulose/utils/benchmark_results.py
cellulose/utils/csv_utils.py
cellulose/utils/devices.py
cellulose/utils/engines.py
cellulose/utils/numpy.py
cellulose/validation/__init__.py
cellulose/validation/validation.py
cellulose_sdk-0.0.3.dist-info/LICENSE
cellulose_sdk-0.0.3.dist-info/METADATA
cellulose_sdk-0.0.3.dist-info/WHEEL
cellulose_sdk-0.0.3.dist-info/top_level.txt
cellulose_sdk-0.0.3.dist-info/RECORD
